sender.py
sender-0.3.dist-info/DESCRIPTION.rst
sender-0.3.dist-info/METADATA
sender-0.3.dist-info/metadata.json
sender-0.3.dist-info/RECORD
sender-0.3.dist-info/top_level.txt
sender-0.3.dist-info/WHEEL
